tello_solectric_pl/__init__.py
tello_solectric_pl/tello_solectric_pl.py
tello_solectric_pl-0.0.5.dist-info/METADATA
tello_solectric_pl-0.0.5.dist-info/WHEEL
tello_solectric_pl-0.0.5.dist-info/top_level.txt
tello_solectric_pl-0.0.5.dist-info/RECORD
