Metadata-Version: 2.1
Name: tello-solectric-pl
Version: 0.0.5
Summary: Biblioteka dla wsparcia nauczycieli w Polsce dla dronów Tello-EDU oraz Ryzen TT (z wyświetlaczem LCD)
Home-page: https://solectric.pl
Author: Adam Jurkiewicz
Author-email: adam@jurkiewicz.tech
License: UNKNOWN
Keywords: Dron Tello TelloEDU Ryzen RyzenTT DJI
Platform: UNKNOWN
Classifier: Programming Language :: Python :: 3
Classifier: License :: OSI Approved :: GNU General Public License v3 (GPLv3)
Classifier: Operating System :: OS Independent
Classifier: Intended Audience :: Education
Requires-Python: >=3.8
Requires-Dist: djitellopy
